README.md
setup.py
pytorch_stream_dataloader/__init__.py
pytorch_stream_dataloader/stream_dataloader.py
pytorch_stream_dataloader/stream_dataset.py
pytorch_stream_dataloader/utils.py
pytorch_stream_dataloader.egg-info/PKG-INFO
pytorch_stream_dataloader.egg-info/SOURCES.txt
pytorch_stream_dataloader.egg-info/dependency_links.txt
pytorch_stream_dataloader.egg-info/requires.txt
pytorch_stream_dataloader.egg-info/top_level.txt